log_aggregator_server/__init__.py
log_aggregator_server/log_aggregator_server.py
log_aggregator_server/process.py
log_aggregator_server/system.py
log_aggregator_server/user_log.py
log_aggregator_server-0.2.1.data/scripts/run_log_aggregator
log_aggregator_server-0.2.1.dist-info/AUTHORS.rst
log_aggregator_server-0.2.1.dist-info/LICENSE
log_aggregator_server-0.2.1.dist-info/METADATA
log_aggregator_server-0.2.1.dist-info/WHEEL
log_aggregator_server-0.2.1.dist-info/top_level.txt
log_aggregator_server-0.2.1.dist-info/RECORD
