Metadata-Version: 2.1
Name: log-aggregator-server
Version: 0.2.1
Summary: Log Aggregator Server
Home-page: https://github.com/Trumble0921/log_aggregator_server
Author: Trumble0921
Author-email: joonyeolsim@gmail.com
License: MIT license
Keywords: log_aggregator_server
Platform: UNKNOWN
Classifier: Development Status :: 2 - Pre-Alpha
Classifier: Intended Audience :: Developers
Classifier: License :: OSI Approved :: MIT License
Classifier: Natural Language :: English
Classifier: Programming Language :: Python :: 2
Classifier: Programming Language :: Python :: 2.7
Classifier: Programming Language :: Python :: 3
Classifier: Programming Language :: Python :: 3.4
Classifier: Programming Language :: Python :: 3.5
Classifier: Programming Language :: Python :: 3.6
Classifier: Programming Language :: Python :: 3.7
Requires-Dist: psutil
